model_analyzer/__init__.py
model_analyzer/dl_models.py
model_analyzer/ml_models.py
model_analyzer/gridsearch_cv/__init__.py
model_analyzer/gridsearch_cv/gridsearch_model.py
model_analyzer/models/__init__.py
model_analyzer/models/classification.py
model_analyzer/models/regression.py
model_analyzer/plot/__init__.py
model_analyzer/plot/regression_plot.py
model_analyzer/score_model/__init__.py
model_analyzer/score_model/classification_score.py
model_analyzer/score_model/regression_score.py
model_performance_investigator-1.0.5.dist-info/LICENSE.txt
model_performance_investigator-1.0.5.dist-info/METADATA
model_performance_investigator-1.0.5.dist-info/WHEEL
model_performance_investigator-1.0.5.dist-info/top_level.txt
model_performance_investigator-1.0.5.dist-info/RECORD
