Metadata-Version: 2.1
Name: model-performance-investigator
Version: 1.0.5
Summary: Package give idea of a models performance based on given data
Home-page: https://github.com/srikandan/model-evaluation
Author: Srikandan Raju, Sathish Anandha
Author-email: kandan.sri15@gmail.com, sathishvp7@gmail.com
License: UNKNOWN
Platform: UNKNOWN
Classifier: Programming Language :: Python :: 3
Classifier: License :: OSI Approved :: MIT License
Classifier: Operating System :: OS Independent
Requires-Python: >=3.6
Requires-Dist: tensorflow
Requires-Dist: keras
Requires-Dist: mxnet
Requires-Dist: scikit-learn
Requires-Dist: numpy
Requires-Dist: pandas
Requires-Dist: statsmodels
Requires-Dist: xgboost
Requires-Dist: scipy
